// class version 50.0 (50)
// access flags 0x401
public abstract class TEnergySink$$3$class {


  // access flags 0x9
  public static $init$(LTEnergySink$$3;)V
    RETURN
    MAXSTACK = 1
    MAXLOCALS = 1

  // access flags 0x9
  public static bindPart(LTEnergySink$$3;Lcodechicken/multipart/TMultiPart;)V
    ALOAD 0
    ALOAD 1
    INVOKEINTERFACE TEnergySink$$3.TEnergySink$$3$$super$bindPart (Lcodechicken/multipart/TMultiPart;)V
    ALOAD 1
    INSTANCEOF ic2/api/energy/tile/IEnergySink
    IFEQ L0
    ALOAD 0
    ALOAD 1
    CHECKCAST ic2/api/energy/tile/IEnergySink
    INVOKEINTERFACE TEnergySink$$3.TEnergySink$$3$$impl_$eq (Lic2/api/energy/tile/IEnergySink;)V
   L0
   FRAME FULL [TEnergySink$$3 codechicken/multipart/TMultiPart] []
    RETURN
    MAXSTACK = 2
    MAXLOCALS = 2

  // access flags 0x9
  public static partRemoved(LTEnergySink$$3;Lcodechicken/multipart/TMultiPart;I)V
    ALOAD 0
    ALOAD 1
    ILOAD 2
    INVOKEINTERFACE TEnergySink$$3.TEnergySink$$3$$super$partRemoved (Lcodechicken/multipart/TMultiPart;I)V
    ALOAD 1
    ALOAD 0
    INVOKEINTERFACE TEnergySink$$3.TEnergySink$$3$$impl ()Lic2/api/energy/tile/IEnergySink;
    IF_ACMPNE L0
    ALOAD 0
    ACONST_NULL
    INVOKEINTERFACE TEnergySink$$3.TEnergySink$$3$$impl_$eq (Lic2/api/energy/tile/IEnergySink;)V
   L0
   FRAME FULL [TEnergySink$$3 codechicken/multipart/TMultiPart I] []
    RETURN
    MAXSTACK = 3
    MAXLOCALS = 3

  // access flags 0x9
  public static canAddPart(LTEnergySink$$3;Lcodechicken/multipart/TMultiPart;)Z
    ALOAD 0
    INVOKEINTERFACE TEnergySink$$3.TEnergySink$$3$$impl ()Lic2/api/energy/tile/IEnergySink;
    IFNULL L0
    ALOAD 1
    INSTANCEOF ic2/api/energy/tile/IEnergySink
    IFEQ L0
    ICONST_0
    IRETURN
   L0
   FRAME FULL [TEnergySink$$3 codechicken/multipart/TMultiPart] []
    ALOAD 0
    ALOAD 1
    INVOKEINTERFACE TEnergySink$$3.TEnergySink$$3$$super$canAddPart (Lcodechicken/multipart/TMultiPart;)Z
    IRETURN
    MAXSTACK = 2
    MAXLOCALS = 2

  // access flags 0x9
  public static getDemandedEnergy(LTEnergySink$$3;)D
    ALOAD 0
    INVOKEINTERFACE TEnergySink$$3.TEnergySink$$3$$impl ()Lic2/api/energy/tile/IEnergySink;
    INVOKEINTERFACE ic2/api/energy/tile/IEnergySink.getDemandedEnergy ()D
    DRETURN
    MAXSTACK = 2
    MAXLOCALS = 1

  // access flags 0x9
  public static getSinkTier(LTEnergySink$$3;)I
    ALOAD 0
    INVOKEINTERFACE TEnergySink$$3.TEnergySink$$3$$impl ()Lic2/api/energy/tile/IEnergySink;
    INVOKEINTERFACE ic2/api/energy/tile/IEnergySink.getSinkTier ()I
    IRETURN
    MAXSTACK = 1
    MAXLOCALS = 1

  // access flags 0x9
  public static injectEnergy(LTEnergySink$$3;Lnet/minecraftforge/common/util/ForgeDirection;DD)D
    ALOAD 0
    INVOKEINTERFACE TEnergySink$$3.TEnergySink$$3$$impl ()Lic2/api/energy/tile/IEnergySink;
    ALOAD 1
    DLOAD 2
    DLOAD 4
    INVOKEINTERFACE ic2/api/energy/tile/IEnergySink.injectEnergy (Lnet/minecraftforge/common/util/ForgeDirection;DD)D
    DRETURN
    MAXSTACK = 6
    MAXLOCALS = 6

  // access flags 0x9
  public static acceptsEnergyFrom(LTEnergySink$$3;Lnet/minecraft/tileentity/TileEntity;Lnet/minecraftforge/common/util/ForgeDirection;)Z
    ALOAD 0
    INVOKEINTERFACE TEnergySink$$3.TEnergySink$$3$$impl ()Lic2/api/energy/tile/IEnergySink;
    ALOAD 1
    ALOAD 2
    INVOKEINTERFACE ic2/api/energy/tile/IEnergySink.acceptsEnergyFrom (Lnet/minecraft/tileentity/TileEntity;Lnet/minecraftforge/common/util/ForgeDirection;)Z
    IRETURN
    MAXSTACK = 3
    MAXLOCALS = 3

  // access flags 0x9
  public static copyFrom(LTEnergySink$$3;Lcodechicken/multipart/TileMultipart;)V
    ALOAD 0
    ALOAD 1
    INVOKEINTERFACE TEnergySink$$3.TEnergySink$$3$$super$copyFrom (Lcodechicken/multipart/TileMultipart;)V
    ALOAD 1
    INSTANCEOF TEnergySink$$3
    IFEQ L0
    ALOAD 0
    ALOAD 1
    INVOKEINTERFACE TEnergySink$$3.TEnergySink$$3$$impl ()Lic2/api/energy/tile/IEnergySink;
    INVOKEINTERFACE TEnergySink$$3.TEnergySink$$3$$impl_$eq (Lic2/api/energy/tile/IEnergySink;)V
   L0
    RETURN
    MAXSTACK = 2
    MAXLOCALS = 2
}
